jps_algo/__init__.py
jps_algo/main.py
jps_algo/utils/__init__.py
jps_algo/utils/algo.py
jps_algo/utils/merge.py
jps_algo/utils/operation.py
jps_algo-0.1.3.dist-info/WHEEL
jps_algo-0.1.3.dist-info/METADATA
jps_algo-0.1.3.dist-info/RECORD
